<annotation>
	<folder>image</folder>
	<filename>IMG_20200526_195049.jpg</filename>
	<path>/home/rachita/Desktop/Test/image/IMG_20200526_195049.jpg</path>
	<source>
		<database>Unknown</database>
	</source>
	<size>
		<width>4000</width>
		<height>3000</height>
		<depth>3</depth>
	</size>
	<segmented>0</segmented>
	<object>
		<name>and</name>
		<pose>Unspecified</pose>
		<truncated>0</truncated>
		<difficult>0</difficult>
		<bndbox>
			<xmin>1252</xmin>
			<ymin>777</ymin>
			<xmax>1852</xmax>
			<ymax>1812</ymax>
		</bndbox>
	</object>
	<object>
		<name>and</name>
		<pose>Unspecified</pose>
		<truncated>0</truncated>
		<difficult>0</difficult>
		<bndbox>
			<xmin>2702</xmin>
			<ymin>1567</ymin>
			<xmax>3337</xmax>
			<ymax>2627</ymax>
		</bndbox>
	</object>
	<object>
		<name>not</name>
		<pose>Unspecified</pose>
		<truncated>0</truncated>
		<difficult>0</difficult>
		<bndbox>
			<xmin>1862</xmin>
			<ymin>1162</ymin>
			<xmax>2042</xmax>
			<ymax>1347</ymax>
		</bndbox>
	</object>
	<object>
		<name>not</name>
		<pose>Unspecified</pose>
		<truncated>0</truncated>
		<difficult>0</difficult>
		<bndbox>
			<xmin>3337</xmin>
			<ymin>1947</ymin>
			<xmax>3472</xmax>
			<ymax>2112</ymax>
		</bndbox>
	</object>
</annotation>
