<annotation>
	<folder>image</folder>
	<filename>IMG_20200526_183818.jpg</filename>
	<path>/home/rachita/Desktop/Test/image/IMG_20200526_183818.jpg</path>
	<source>
		<database>Unknown</database>
	</source>
	<size>
		<width>4000</width>
		<height>2906</height>
		<depth>3</depth>
	</size>
	<segmented>0</segmented>
	<object>
		<name>and</name>
		<pose>Unspecified</pose>
		<truncated>0</truncated>
		<difficult>0</difficult>
		<bndbox>
			<xmin>1162</xmin>
			<ymin>505</ymin>
			<xmax>1702</xmax>
			<ymax>1355</ymax>
		</bndbox>
	</object>
	<object>
		<name>and</name>
		<pose>Unspecified</pose>
		<truncated>0</truncated>
		<difficult>0</difficult>
		<bndbox>
			<xmin>2707</xmin>
			<ymin>1425</ymin>
			<xmax>3277</xmax>
			<ymax>2325</ymax>
		</bndbox>
	</object>
	<object>
		<name>not</name>
		<pose>Unspecified</pose>
		<truncated>0</truncated>
		<difficult>0</difficult>
		<bndbox>
			<xmin>1717</xmin>
			<ymin>820</ymin>
			<xmax>1842</xmax>
			<ymax>965</ymax>
		</bndbox>
	</object>
	<object>
		<name>not</name>
		<pose>Unspecified</pose>
		<truncated>0</truncated>
		<difficult>0</difficult>
		<bndbox>
			<xmin>3282</xmin>
			<ymin>1750</ymin>
			<xmax>3412</xmax>
			<ymax>1890</ymax>
		</bndbox>
	</object>
</annotation>
