<annotation>
	<folder>img</folder>
	<filename>IMG_20200527_235808.jpg</filename>
	<path>/home/rachita/Desktop/test_new/img/IMG_20200527_235808.jpg</path>
	<source>
		<database>Unknown</database>
	</source>
	<size>
		<width>4000</width>
		<height>3000</height>
		<depth>3</depth>
	</size>
	<segmented>0</segmented>
	<object>
		<name>and</name>
		<pose>Unspecified</pose>
		<truncated>0</truncated>
		<difficult>0</difficult>
		<bndbox>
			<xmin>1137</xmin>
			<ymin>442</ymin>
			<xmax>1822</xmax>
			<ymax>1517</ymax>
		</bndbox>
	</object>
	<object>
		<name>and</name>
		<pose>Unspecified</pose>
		<truncated>0</truncated>
		<difficult>0</difficult>
		<bndbox>
			<xmin>2812</xmin>
			<ymin>1512</ymin>
			<xmax>3362</xmax>
			<ymax>2522</ymax>
		</bndbox>
	</object>
</annotation>
